common/util.svh
// source: https://github.com/yuri-panchul/systemverilog-homework/blob/main/common/util.svh

`define PD(SYMBOL) $sformatf("SYMBOL:%0d", SYMBOL)
`define PB(SYMBOL) $sformatf("SYMBOL:%b", SYMBOL)
`define PH(SYMBOL) $sformatf("SYMBOL:%h", SYMBOL)
`define PF(SYMBOL) $sformatf("SYMBOL:%f", SYMBOL)

`define PF_BITS(SYMBOL) $sformatf("SYMBOL:%f", $bitstoreal(SYMBOL))
`define PG_BITS(SYMBOL) $sformatf("SYMBOL:%g", $bitstoreal(SYMBOL))

`ifdef __ICARUS__
    `define ISUNKNOWN(a) ((^ a) === 1'bx)
`else
    `define ISUNKNOWN(a) $isunknown(a)
`endif

util_modules/flipflop.sv
module flipflop#(
     .size = 16
)( // rename + parametrise
     input clk,
     input rst,
     input valid,
     input  logic[size - 1    :    0] data,
     output logic[size - 1    :    0] out
);

     logic[15: 0] reg_data;
     always_ff @(posedge clk) begin
          if(rst) begin
               reg_data <= '0;
          else if(valid)
               reg_data <= data;
     end

     assign out = reg_data;

endmodule

overdrive_clamp.sv
module overdrive_clamp #(
	parameter bits_per_level = 12
) (
	input int signed x,
	output int signed out
);
 
localparam one_level = 1 << bits_per_level;
localparam half_level = one_level / 2;
 
int signed dx;
assign dx = int'(x);
 
always_comb begin
	if ( dx >= one_level )
		out = half_level;
	else if ( dx <= -one_level)
		out = -half_level;
	else
		out = ((dx*3) + (dx * dx / one_level * dx / one_level)) / 4;
end

endmodule

gain.sv
module gain #(
     parameter bits_per_level = 12
) (
     input shortint signed a, b,
     output int signed res
);
     
     int signed t;
     assign t = (int'(a) * int'(b)) >>> bits_per_level;
     assign res = t;

endmodule

overdrive.sv
module overdrive #(
     parameter bits_per_level = 12,
               bits_per_gain_frac = 4
)(
     input shortint signed signal_in,
     input shortint signed gain,
     output shortint signed signal_out
);
     
     int signed ss_signal, ss_clamped_signal;
     gain #(bits_per_gain_frac)
          m_gain(.a(signal_in), .b(gain), .res(ss_signal));
     
     overdrive_clamp #(bits_per_level)
          m_clamp(.x(ss_signal), .out(ss_clamped_signal));
     
     assign signal_out = shortint'(ss_clamped_signal);
     
endmodule

effects_pipeline.sv
module effects_pipline #(
     parameter bits_per_level = 12,
               bits_per_gain_frac = 4   // fractional part of input gain
) (
     input clk,
     input rst,

     // effects parameters 
	input  [10: 0] gain_value,    // bits_per_gain_frac bits for fraction part, 10 - bits_per_gain_frac bits for integer part


     input          valid,
     input  [12: 0] sample_in,
     output [15: 0] sample_out
);

// Overdrive
     logic [15  :0   ]   overdrive_in;

     flipflop#(
          .size(16)
     ) i_overdrive_ff (
          .clk(clk),
          .rst(rst),
          .valid(valid),
          .data(sample_in),
          .out(overdrive_in)
     );

     shortint signed ss_ovrd_in, ss_gain;

     assign ss_ovrd_in   = shortint'(overdrive_in);
     assign ss_gain      = shortint'(gain_value);

     wire [15  :0   ] overdrive_out;
     overdrive #(
          .bits_per_level(bits_per_level),
          .bits_per_gain_frac(bits_per_gain_frac)
     ) i_ovrd (
          .signal_in(ss_ovrd_in),
          .gain(ss_gain),
          .signal_out(overdrive_out)
     );

// Output
     flipflop#(
          .size(16)
     ) i_output_ff (
          .clk(clk),
          .rst(rst),
          .valid(valid),
          .data(overdrive_out),
          .out(sample_out)
     );
     
endmodule

verification/tb_effect_pipeline.sv
//----------------------------------------------------------------------------
// Testbench based on https://github.com/yuri-panchul/systemverilog-homework/
//----------------------------------------------------------------------------

`include "util.svh"

module testbench;
    localparam SLEN = 16;
    //--------------------------------------------------------------------------
    // Signals to drive Device Under Test - DUT

    logic               clk;
    logic               rst;

    // logic               arg_vld;
    logic  [SLEN - 1:0] sample_in;

    // wire                res_vld;
    wire   [SLEN - 1:0] sample_out;

    //--------------------------------------------------------------------------
    // Instantiating DUT

    effects_pipline dut (
        .clk(clk), // slow !?!
        .rst('0),
        .valid('1),
		.gain_value(10'd20),
		.sample_in(sample_in),
		.sample_out(sample_out)
    );

    //--------------------------------------------------------------------------
    // Driving clk

    initial
    begin
        clk = '1;

        forever
        begin
            # 5 clk = ~ clk;
        end
    end

    //------------------------------------------------------------------------
    // Reset

    task reset ();

        rst <= 'x;
        repeat (3) @ (posedge clk);
        rst <= '1;
        repeat (3) @ (posedge clk);
        rst <= '0;

    endtask

    //--------------------------------------------------------------------------
    // Driving stimulus

    localparam TIMEOUT = 5000;

    task run ();

        $display ("--------------------------------------------------");
        $display ("Running %m");

        // Init and reset

        // arg_vld <= '0;
        reset ();

        // Direct testing - a single test

        sample_in       <=  (SLEN)'(12);
        // arg_vld <= '1;

        @ (posedge clk);
        // arg_vld <= '0;

        // while (~ res_vld)
        //     @ (posedge clk);

        // Direct testing - a group of tests

        for (int i = 0; i < 100; i = i * 3 + 1)
        begin
            sample_in       <= (SLEN)'(i);

            // arg_vld <= '1;

            @ (posedge clk);
            // arg_vld <= '0;

            // while (~ res_vld)
                // @ (posedge clk);
        end

        // Random testing

        repeat (20)
        begin
            sample_in       <= 12'($urandom());

            // arg_vld <= '1;

            @ (posedge clk);
            // arg_vld <= '0;

            // while (~ res_vld)
                // @ (posedge clk);
        end

    endtask

    //--------------------------------------------------------------------------
    // Running testbench

    initial
    begin
        `ifdef __ICARUS__
            // Uncomment the following line
            // to generate a VCD file and analyze it using GTKwave

            $dumpvars;
        `endif

        run ();

        $finish;
    end

    //--------------------------------------------------------------------------
    // Logging

    int unsigned cycle = 0;

    always @ (posedge clk)
    begin
        $write ("%s time %7d cycle %5d", `__FILE__, $time, cycle);
        cycle <= cycle + 1'b1;

        // if (rst)
        //     $write (" rst");
        // else
        //     $write ("    ");

        // if (arg_vld)
        //     // Optionnaly change to `PF_BITS optionally
        //     $write (" arg %s %s %s", `PG_BITS (a), `PG_BITS (b), `PG_BITS (c) );
        // else
        //     $write ("                                     ");

        // if (res_vld)
        //     $write (" res %s", `PG_BITS(res) );

        /// $write("in: ");

        $display;
    end

    //--------------------------------------------------------------------------
    // Modeling and checking

    logic [SLEN - 1:0] queue [$];
    logic [SLEN - 1:0] res_expected;

    logic was_reset = 0;

    // Blocking assignments are okay in this synchronous always block, because
    // data is passed using queue and all the checks are inside that always
    // block, so no race condition is possible

    // verilator lint_off BLKSEQ

    always @ (posedge clk)
    begin
        if (rst)
        begin
            queue = {};
            was_reset = 1;
        end
        else if (was_reset)
        begin
            // if (arg_vld)
            // begin
            //     res_expected = $realtobits( $bitstoreal (b) * $bitstoreal (b) - 4 * $bitstoreal (a) * $bitstoreal (c) );

            //     queue.push_back (res_expected);
            // end

            // if (res_vld)
            // begin
            //     if (queue.size () == 0)
            //     begin
            //         $display ("FAIL %s: unexpected result %s",
            //             `__FILE__, `PG_BITS (res) );

            //         $finish;
            //     end
            //     else
            //     begin
            //         `ifdef __ICARUS__
            //             // Some version of Icarus has a bug, and this is a workaround
            //             res_expected = queue [0];
            //             queue.delete (0);
            //         `else
            //             res_expected = queue.pop_front ();
            //         `endif

            //         err_expected = is_err ( res_expected );
            //         if (err !== err_expected )
            //         begin
            //             $display ("FAIL %s: error mismatch. Expected %s, actual %s",
            //                 `__FILE__, `PB (err_expected), `PB (err) );

            //             $finish;
            //         end
            //         else if ( ( err_expected === 1'b0 ) && ( res !== res_expected ) )
            //         begin
            //             $display ("FAIL %s: res mismatch. Expected %s, actual %s",
            //                 `__FILE__, `PG_BITS (res_expected), `PG_BITS (res) );

            //             $finish;
            //         end
            //     end
            // end
        end
    end

    // verilator lint_on BLKSEQ

    //----------------------------------------------------------------------

    final
    begin
        if (queue.size () == 0)
        begin
            $display ("PASS %s", `__FILE__);
        end
        else
        begin
            $write ("FAIL %s: data is left sitting in the model queue:",
                `__FILE__);

            for (int i = 0; i < queue.size (); i ++)
                $write (" %h", queue [queue.size () - i - 1]);

            $display;
        end
    end

    //----------------------------------------------------------------------
    // Performance counters

    logic [32:0] n_cycles, arg_cnt, res_cnt;

    always @ (posedge clk)
        if (rst)
        begin
            n_cycles <= '0;
            arg_cnt  <= '0;
            res_cnt  <= '0;
        end
        else
        begin
            n_cycles <= n_cycles + 1'd1;

            // if (arg_vld)
            //     arg_cnt <= arg_cnt + 1'd1;

            // if (res_vld)
            //     res_cnt <= res_cnt + 1'd1;
        end

    //----------------------------------------------------------------------

    final
        $display ("\n\nnumber of transfers : arg %0d res %0d per %0d cycles",
            arg_cnt, res_cnt, n_cycles);

    //----------------------------------------------------------------------
    // Setting timeout against hangs

    initial
    begin
        repeat (TIMEOUT) @ (posedge clk);
        $display ("FAIL %s: timeout!", `__FILE__);
        $finish;
    end

endmodule

util_modules/fixed_math.sv
// c = a * b
// 'c' have double width (i.e. operand_size*2)
module fixed_multiply#(
    parameter  fractional_size     = 12,
               operand_size        = 32
) (
    input  logic signed[operand_size - 1: 0] a, 
    input  logic signed[operand_size - 1: 0] b,
    output logic signed[operand_size*2-1: 0] c
);

     logic [(operand_size)*2 - 1: 0] temp_result; // Temporary result to handle overflow
     logic [(operand_size)*2 - 1: 0] partial_products [(operand_size) * 2]; // Array to store partial products

     logic [(operand_size)*2 - 1: 0] a_extended;
     logic [(operand_size)*2 - 1: 0] b_extended;

     signed_expand #(
          .operand_size(operand_size),
          .expansion_size(operand_size)
     ) i_a_expand (
          .in(a),
          .out(a_extended)
     );
     signed_expand #(
          .operand_size(operand_size),
          .expansion_size(operand_size)
     ) i_b_expand (
          .in(b),
          .out(b_extended)
     );   

     // Generate block to calculate partial products
     genvar i;
     generate
          for (i = 0; i < (operand_size) * 2; i = i + 1) begin : mult_loop
               assign partial_products[i] = b_extended[i] ? (a_extended << i) : 0; // Shift and conditionally select
          end
     endgenerate

     //  sum all partial products
     always_comb begin
          temp_result = 0;  
          for (int j = 0; j < (operand_size)*2; j++) begin
               temp_result = temp_result + partial_products[j]; // Accumulate partial products
          end
     end

     // Assign the lower bits to the output
     assign c = $signed(temp_result) >>> fractional_size;

endmodule

// converts in[operand_size-1: 0] -> out[operand_size+expansion_size-1: 0] according to the sign
module signed_expand #(
     parameter operand_size   = 12,
               expansion_size = 4 
) (
     input logic[operand_size-1: 0]                    in, 
     output logic[operand_size+expansion_size-1: 0]    out
);
     logic sign;
     
     always_comb begin
          sign = (in & ((operand_size)'(1) << (operand_size - 1))) >> (operand_size - 1);

          out = {(expansion_size)'(0) - sign, in};
     end
endmodule

tmp/dump.vcd
$date
	Tue Dec 24 00:12:07 2024
$end
$version
	Icarus Verilog
$end
$timescale
	1s
$end
$scope module fixed_multiply $end
$var wire 32 ! a [31:0] $end
$var wire 32 " b [31:0] $end
$var wire 32 # c [31:0] $end
$upscope $end
$scope module testbench $end
$var wire 16 $ sample_out [15:0] $end
$var reg 33 % arg_cnt [32:0] $end
$var reg 1 & clk $end
$var reg 33 ' n_cycles [32:0] $end
$var reg 33 ( res_cnt [32:0] $end
$var reg 1 ) rst $end
$var reg 16 * sample_in [15:0] $end
$var reg 1 + was_reset $end
$var reg 32 , cycle [31:0] $end
$scope module dut $end
$var wire 1 & clk $end
$var wire 11 - gain_value [10:0] $end
$var wire 1 . rst $end
$var wire 13 / sample_in [12:0] $end
$var wire 1 0 valid $end
$var wire 16 1 ss_ovrd_in [15:0] $end
$var wire 16 2 ss_gain [15:0] $end
$var wire 16 3 sample_out [15:0] $end
$var wire 16 4 overdrive_out [15:0] $end
$var wire 16 5 overdrive_in [15:0] $end
$scope module i_output_ff $end
$var wire 1 & clk $end
$var wire 16 6 out [15:0] $end
$var wire 1 . rst $end
$var wire 1 0 valid $end
$var wire 16 7 data [15:0] $end
$var reg 16 8 reg_data [15:0] $end
$upscope $end
$scope module i_overdrive_ff $end
$var wire 1 & clk $end
$var wire 16 9 data [15:0] $end
$var wire 1 . rst $end
$var wire 1 0 valid $end
$var wire 16 : out [15:0] $end
$var reg 16 ; reg_data [15:0] $end
$upscope $end
$scope module i_ovrd $end
$var wire 16 < gain [15:0] $end
$var wire 16 = signal_in [15:0] $end
$var wire 32 > ss_signal [31:0] $end
$var wire 32 ? ss_clamped_signal [31:0] $end
$var wire 16 @ signal_out [15:0] $end
$scope module m_clamp $end
$var wire 32 A x [31:0] $end
$var wire 32 B dx [31:0] $end
$var integer 32 C out [31:0] $end
$upscope $end
$scope module m_gain $end
$var wire 16 D a [15:0] $end
$var wire 16 E b [15:0] $end
$var wire 32 F res [31:0] $end
$var wire 32 G t [31:0] $end
$upscope $end
$upscope $end
$upscope $end
$scope begin $ivl_for_loop1 $end
$var integer 32 H i [31:0] $end
$upscope $end
$scope task reset $end
$upscope $end
$scope task run $end
$scope begin $ivl_for_loop0 $end
$var integer 32 I i [31:0] $end
$upscope $end
$upscope $end
$upscope $end
$enddefinitions $end
#0
$dumpvars
b0 I
b0 H
b0 G
b0 F
b10100 E
b0 D
b0 C
b0 B
b0 A
b0 @
b0 ?
b0 >
b0 =
b10100 <
b0xxxxxxxxxxxxx ;
b0xxxxxxxxxxxxx :
b0xxxxxxxxxxxxx 9
b0 8
b0 7
b0 6
b0xxxxxxxxxxxxx 5
b0 4
b0 3
b10100 2
b0 1
10
bx /
0.
b10100 -
b0 ,
0+
bx *
x)
bx (
bx '
1&
bx %
b0 $
b0 #
bz "
bz !
$end
#5
0&
#10
b1 ,
1&
#15
0&
#20
b10 ,
1&
#25
0&
#30
1)
b11 ,
1&
#35
0&
#40
b0 (
b0 %
b0 '
b100 ,
1+
1&
#45
0&
#50
b101 ,
1&
#55
0&
#60
b1100 9
b1100 /
b1100 *
b110 ,
0)
1&
#65
0&
#70
b1011 4
b1011 7
b1011 @
b1011 ?
b1011 C
b0 9
b0 /
b1111 >
b1111 A
b1111 B
b1111 F
b1111 G
b0 *
b111 ,
b1 '
b1100 1
b1100 =
b1100 D
b1100 5
b1100 :
b1100 ;
1&
#75
0&
#80
b0 4
b0 7
b0 @
b0 ?
b0 C
b0 >
b0 A
b0 B
b0 F
b0 G
b1 9
b1 /
b0 1
b0 =
b0 D
b0 5
b0 :
b0 ;
b1011 $
b1011 3
b1011 6
b1011 8
b10 '
b1000 ,
b1 *
b1 I
1&
#85
0&
#90
b100 9
b100 /
b1 >
b1 A
b1 B
b1 F
b1 G
b100 *
b1001 ,
b11 '
b0 $
b0 3
b0 6
b0 8
b1 1
b1 =
b1 D
b1 5
b1 :
b1 ;
b100 I
1&
#95
0&
#100
b11 4
b11 7
b11 @
b11 ?
b11 C
b101 >
b101 A
b101 B
b101 F
b101 G
b1101 9
b1101 /
b100 1
b100 =
b100 D
b100 5
b100 :
b100 ;
b100 '
b1010 ,
b1101 *
b1101 I
1&
#105
0&
#110
b1100 4
b1100 7
b1100 @
b1100 ?
b1100 C
b101000 9
b101000 /
b10000 >
b10000 A
b10000 B
b10000 F
b10000 G
b101000 *
b1011 ,
b101 '
b11 $
b11 3
b11 6
b11 8
b1101 1
b1101 =
b1101 D
b1101 5
b1101 :
b1101 ;
b101000 I
1&
#115
0&
#120
b100101 4
b100101 7
b100101 @
b100101 ?
b100101 C
b10100100100 9
b10100100100 /
b110010 >
b110010 A
b110010 B
b110010 F
b110010 G
b10100100100 *
b101000 1
b101000 =
b101000 D
b101000 5
b101000 :
b101000 ;
b1100 $
b1100 3
b1100 6
b1100 8
b110 '
b1100 ,
b1111001 I
1&
#125
0&
#130
b10100010100 4
b10100010100 7
b10100010100 @
b10100010100 ?
b10100010100 C
b11001101101 >
b11001101101 A
b11001101101 B
b11001101101 F
b11001101101 G
b111010000001 9
b111010000001 /
b1101 ,
b111 '
b100101 $
b100101 3
b100101 6
b100101 8
b10100100100 1
b10100100100 =
b10100100100 D
b10100100100 5
b10100100100 :
b10100100100 ;
b111010000001 *
1&
#135
0&
#140
b100000000000 4
b100000000000 7
b100000000000 @
b100000000000 ?
b100000000000 C
b11000001001 9
b11000001001 /
b1001000100001 >
b1001000100001 A
b1001000100001 B
b1001000100001 F
b1001000100001 G
b11000001001 *
b111010000001 1
b111010000001 =
b111010000001 D
b111010000001 5
b111010000001 :
b111010000001 ;
b10100010100 $
b10100010100 3
b10100010100 6
b10100010100 8
b1000 '
b1110 ,
1&
#145
0&
#150
b11000010011 4
b11000010011 7
b11000010011 @
b11000010011 ?
b11000010011 C
b11110001011 >
b11110001011 A
b11110001011 B
b11110001011 F
b11110001011 G
b11001100011 9
b11001100011 /
b1111 ,
b1001 '
b100000000000 $
b100000000000 3
b100000000000 6
b100000000000 8
b11000001001 1
b11000001001 =
b11000001001 D
b11000001001 5
b11000001001 :
b11000001001 ;
b11001100011 *
1&
#155
0&
#160
b11001111011 4
b11001111011 7
b11001111011 @
b11001111011 ?
b11001111011 C
b101100001101 9
b101100001101 /
b11111111011 >
b11111111011 A
b11111111011 B
b11111111011 F
b11111111011 G
b101100001101 *
b11001100011 1
b11001100011 =
b11001100011 D
b11001100011 5
b11001100011 :
b11001100011 ;
b11000010011 $
b11000010011 3
b11000010011 6
b11000010011 8
b1010 '
b10000 ,
1&
#165
0&
#170
b110011101110 4
b110011101110 7
b110011101110 @
b110011101110 ?
b110011101110 C
b110111010000 >
b110111010000 A
b110111010000 B
b110111010000 F
b110111010000 G
b100110001101 9
b100110001101 /
b10001 ,
b1011 '
b11001111011 $
b11001111011 3
b11001111011 6
b11001111011 8
b101100001101 1
b101100001101 =
b101100001101 D
b101100001101 5
b101100001101 :
b101100001101 ;
b100110001101 *
1&
#175
0&
#180
b101010011101 4
b101010011101 7
b101010011101 @
b101010011101 ?
b101010011101 C
b10001100101 9
b10001100101 /
b101111110000 >
b101111110000 A
b101111110000 B
b101111110000 F
b101111110000 G
b10001100101 *
b100110001101 1
b100110001101 =
b100110001101 D
b100110001101 5
b100110001101 :
b100110001101 ;
b110011101110 $
b110011101110 3
b110011101110 6
b110011101110 8
b1100 '
b10010 ,
1&
#185
0&
#190
b10001000111 4
b10001000111 7
b10001000111 @
b10001000111 ?
b10001000111 C
b10101111110 >
b10101111110 A
b10101111110 B
b10101111110 F
b10101111110 G
b1000010010 9
b1000010010 /
b10011 ,
b1101 '
b101010011101 $
b101010011101 3
b101010011101 6
b101010011101 8
b10001100101 1
b10001100101 =
b10001100101 D
b10001100101 5
b10001100101 :
b10001100101 ;
b1000010010 *
1&
#195
0&
#200
b111110100 4
b111110100 7
b111110100 @
b111110100 ?
b111110100 C
b1100000001 9
b1100000001 /
b1010010110 >
b1010010110 A
b1010010110 B
b1010010110 F
b1010010110 G
b1100000001 *
b1000010010 1
b1000010010 =
b1000010010 D
b1000010010 5
b1000010010 :
b1000010010 ;
b10001000111 $
b10001000111 3
b10001000111 6
b10001000111 8
b1110 '
b10100 ,
1&
#205
0&
#210
b1011011101 4
b1011011101 7
b1011011101 @
b1011011101 ?
b1011011101 C
b1111000001 >
b1111000001 A
b1111000001 B
b1111000001 F
b1111000001 G
b110100001101 9
b110100001101 /
b10101 ,
b1111 '
b111110100 $
b111110100 3
b111110100 6
b111110100 8
b1100000001 1
b1100000001 =
b1100000001 D
b1100000001 5
b1100000001 :
b1100000001 ;
b110100001101 *
1&
#215
0&
#220
b100000000000 4
b100000000000 7
b100000000000 @
b100000000000 ?
b100000000000 C
b101110110 9
b101110110 /
b1000001010000 >
b1000001010000 A
b1000001010000 B
b1000001010000 F
b1000001010000 G
b101110110 *
b110100001101 1
b110100001101 =
b110100001101 D
b110100001101 5
b110100001101 :
b110100001101 ;
b1011011101 $
b1011011101 3
b1011011101 6
b1011011101 8
b10000 '
b10110 ,
1&
#225
0&
#230
b101011111 4
b101011111 7
b101011111 @
b101011111 ?
b101011111 C
b111010011 >
b111010011 A
b111010011 B
b111010011 F
b111010011 G
b110100111101 9
b110100111101 /
b10111 ,
b10001 '
b100000000000 $
b100000000000 3
b100000000000 6
b100000000000 8
b101110110 1
b101110110 =
b101110110 D
b101110110 5
b101110110 :
b101110110 ;
b110100111101 *
1&
#235
0&
#240
b100000000000 4
b100000000000 7
b100000000000 @
b100000000000 ?
b100000000000 C
b11111101101 9
b11111101101 /
b1000010001100 >
b1000010001100 A
b1000010001100 B
b1000010001100 F
b1000010001100 G
b11111101101 *
b110100111101 1
b110100111101 =
b110100111101 D
b110100111101 5
b110100111101 :
b110100111101 ;
b101011111 $
b101011111 3
b101011111 6
b101011111 8
b10010 '
b11000 ,
1&
#245
0&
#250
b100001100001 4
b100001100001 7
b100001100001 @
b100001100001 ?
b100001100001 C
b100111101000 >
b100111101000 A
b100111101000 B
b100111101000 F
b100111101000 G
b11110001100 9
b11110001100 /
b11001 ,
b10011 '
b100000000000 $
b100000000000 3
b100000000000 6
b100000000000 8
b11111101101 1
b11111101101 =
b11111101101 D
b11111101101 5
b11111101101 :
b11111101101 ;
b11110001100 *
1&
#255
0&
#260
b11111100101 4
b11111100101 7
b11111100101 @
b11111100101 ?
b11111100101 C
b100111111001 9
b100111111001 /
b100101101111 >
b100101101111 A
b100101101111 B
b100101101111 F
b100101101111 G
b100111111001 *
b11110001100 1
b11110001100 =
b11110001100 D
b11110001100 5
b11110001100 :
b11110001100 ;
b100001100001 $
b100001100001 3
b100001100001 6
b100001100001 8
b10100 '
b11010 ,
1&
#265
0&
#270
b101100111101 4
b101100111101 7
b101100111101 @
b101100111101 ?
b101100111101 C
b110001110111 >
b110001110111 A
b110001110111 B
b110001110111 F
b110001110111 G
b10011000110 9
b10011000110 /
b11011 ,
b10101 '
b11111100101 $
b11111100101 3
b11111100101 6
b11111100101 8
b100111111001 1
b100111111001 =
b100111111001 D
b100111111001 5
b100111111001 :
b100111111001 ;
b10011000110 *
1&
#275
0&
#280
b10010101110 4
b10010101110 7
b10010101110 @
b10010101110 ?
b10010101110 C
b10011000101 9
b10011000101 /
b10111110111 >
b10111110111 A
b10111110111 B
b10111110111 F
b10111110111 G
b10011000101 *
b10011000110 1
b10011000110 =
b10011000110 D
b10011000110 5
b10011000110 :
b10011000110 ;
b101100111101 $
b101100111101 3
b101100111101 6
b101100111101 8
b10110 '
b11100 ,
1&
#285
0&
#290
b10010101101 4
b10010101101 7
b10010101101 @
b10010101101 ?
b10010101101 C
b10111110110 >
b10111110110 A
b10111110110 B
b10111110110 F
b10111110110 G
b1010101010 9
b1010101010 /
b11101 ,
b10111 '
b10010101110 $
b10010101110 3
b10010101110 6
b10010101110 8
b10011000101 1
b10011000101 =
b10011000101 D
b10011000101 5
b10011000101 :
b10011000101 ;
b1010101010 *
1&
#295
0&
#300
b1010001000 4
b1010001000 7
b1010001000 @
b1010001000 ?
b1010001000 C
b11111100101 9
b11111100101 /
b1101010100 >
b1101010100 A
b1101010100 B
b1101010100 F
b1101010100 G
b11111100101 *
b1010101010 1
b1010101010 =
b1010101010 D
b1010101010 5
b1010101010 :
b1010101010 ;
b10010101101 $
b10010101101 3
b10010101101 6
b10010101101 8
b11000 '
b11110 ,
1&
#305
0&
#310
b100001010110 4
b100001010110 7
b100001010110 @
b100001010110 ?
b100001010110 C
b100111011110 >
b100111011110 A
b100111011110 B
b100111011110 F
b100111011110 G
b1001110111 9
b1001110111 /
b11111 ,
b11001 '
b1010001000 $
b1010001000 3
b1010001000 6
b1010001000 8
b11111100101 1
b11111100101 =
b11111100101 D
b11111100101 5
b11111100101 :
b11111100101 ;
b1001110111 *
1&
#315
0&
#320
b1001010110 4
b1001010110 7
b1001010110 @
b1001010110 ?
b1001010110 C
b1100010100 >
b1100010100 A
b1100010100 B
b1100010100 F
b1100010100 G
b1001110111 1
b1001110111 =
b1001110111 D
b1001110111 5
b1001110111 :
b1001110111 ;
b100001010110 $
b100001010110 3
b100001010110 6
b100001010110 8
b11010 '
b100000 ,
1&
